MANIFEST.in
README.md
setup.py
setuptools_webpack.py
setuptools_webpack.egg-info/PKG-INFO
setuptools_webpack.egg-info/SOURCES.txt
setuptools_webpack.egg-info/dependency_links.txt
setuptools_webpack.egg-info/entry_points.txt
setuptools_webpack.egg-info/top_level.txt