Metadata-Version: 1.1
Name: setuptools-webpack
Version: 0.1.1
Summary: Plugin for setuptools to run webpack
Home-page: https://github.com/CZ-NIC/setuptools_webpack
Author: Jan Musilek
Author-email: jan.musilek@nic.cz
License: GPLv3
Platform: UNKNOWN
Classifier: Development Status :: 4 - Beta
Classifier: Intended Audience :: Developers
Classifier: License :: OSI Approved :: GNU General Public License v3 (GPLv3)
Classifier: Operating System :: OS Independent
Classifier: Programming Language :: Python :: 2
Classifier: Programming Language :: Python :: 2.6
Classifier: Programming Language :: Python :: 2.7
Classifier: Programming Language :: Python :: 3
Classifier: Programming Language :: Python :: 3.5
Classifier: Programming Language :: Python :: 3.6
Classifier: Topic :: Software Development :: Build Tools
